pynvvl/__init__.py
pynvvl/_nvvl.cpython-34m.so
pynvvl/_lib/libavcodec.so.57
pynvvl/_lib/libavfilter.so.6
pynvvl/_lib/libavformat.so.57
pynvvl/_lib/libavutil.so.55
pynvvl/_lib/libnvvl.so
pynvvl_cuda90-0.0.3a2.dist-info/METADATA
pynvvl_cuda90-0.0.3a2.dist-info/RECORD
pynvvl_cuda90-0.0.3a2.dist-info/WHEEL
pynvvl_cuda90-0.0.3a2.dist-info/top_level.txt
